eodag_labextension/__init__.py
eodag_labextension/_version.py
eodag_labextension/config.py
eodag_labextension/handlers.py
eodag_labextension/labextension/package.json
eodag_labextension/labextension/schemas/eodag-labextension/package.json.orig
eodag_labextension/labextension/schemas/eodag-labextension/plugin.json
eodag_labextension/labextension/static/066daca850d8ffbef007.png
eodag_labextension/labextension/static/1082.728114e7566d47618235.js
eodag_labextension/labextension/static/1369.c39385356205983beb38.js
eodag_labextension/labextension/static/1440.e59109761f8061723618.js
eodag_labextension/labextension/static/1440.e59109761f8061723618.js.LICENSE.txt
eodag_labextension/labextension/static/1694.308b15c30ca1f61421cd.js
eodag_labextension/labextension/static/1694.308b15c30ca1f61421cd.js.LICENSE.txt
eodag_labextension/labextension/static/1868.61fb0264e382eb7dbd5e.js
eodag_labextension/labextension/static/1dbbe9d028e292f36fcb.png
eodag_labextension/labextension/static/2485.05fd71aab6762272d9e0.js
eodag_labextension/labextension/static/2485.05fd71aab6762272d9e0.js.LICENSE.txt
eodag_labextension/labextension/static/2543.c7e0e7ce05e4636872a9.js
eodag_labextension/labextension/static/2543.c7e0e7ce05e4636872a9.js.LICENSE.txt
eodag_labextension/labextension/static/2785.a9fdd4c57ca18b3cbbf1.js
eodag_labextension/labextension/static/2834.6575f3e65304cc89efe2.js
eodag_labextension/labextension/static/2834.6575f3e65304cc89efe2.js.LICENSE.txt
eodag_labextension/labextension/static/328.d65d7f6f1fbdbb63fb93.js
eodag_labextension/labextension/static/331.df7a6e9857b6aef442af.js
eodag_labextension/labextension/static/331.df7a6e9857b6aef442af.js.LICENSE.txt
eodag_labextension/labextension/static/3481.10367a52ad157436329e.js
eodag_labextension/labextension/static/3481.10367a52ad157436329e.js.LICENSE.txt
eodag_labextension/labextension/static/4162.5a417f526443178b1cf3.js
eodag_labextension/labextension/static/4364.168bf0804b9bf221b70a.js
eodag_labextension-5.2.4.dist-info/licenses/LICENSE
eodag_labextension-5.2.4.dist-info/licenses/NOTICE
eodag_labextension-5.2.4.dist-info/METADATA
eodag_labextension-5.2.4.dist-info/WHEEL
eodag_labextension-5.2.4.dist-info/top_level.txt
eodag_labextension-5.2.4.dist-info/RECORD
