Metadata-Version: 2.4
Name: eodag_labextension
Version: 5.2.4
Summary: Searching remote sensed imagery from various image providers
Home-page: https://github.com/CS-SI/eodag-labextension
Author: CS Group
Author-email: eodag@csgroup.space
License: Apache-2.0
Keywords: Jupyter,JupyterLab,JupyterLab3
Platform: Linux
Platform: Mac OS X
Platform: Windows
Classifier: License :: OSI Approved :: Apache Software License
Classifier: Programming Language :: Python
Classifier: Programming Language :: Python :: 3
Classifier: Programming Language :: Python :: 3.9
Classifier: Programming Language :: Python :: 3.10
Classifier: Programming Language :: Python :: 3.11
Classifier: Framework :: Jupyter
Requires-Python: >=3.9
License-File: LICENSE
License-File: NOTICE
Requires-Dist: jupyterlab~=4.0
Requires-Dist: tornado<7.0.0,>=6.4.1
Requires-Dist: notebook<7.0.0,>=6.0.3
Requires-Dist: eodag[notebook]>=3.9.0
Requires-Dist: orjson
Requires-Dist: pydantic
Requires-Dist: pydantic-settings
Requires-Dist: python-dotenv
Provides-Extra: dev
Requires-Dist: black; extra == "dev"
Requires-Dist: pre-commit; extra == "dev"
Requires-Dist: pytest; extra == "dev"
Requires-Dist: shapely; extra == "dev"
Dynamic: author
Dynamic: author-email
Dynamic: classifier
Dynamic: description
Dynamic: description-content-type
Dynamic: home-page
Dynamic: keywords
Dynamic: license
Dynamic: license-file
Dynamic: platform
Dynamic: provides-extra
Dynamic: requires-dist
Dynamic: requires-python
Dynamic: summary
